sensiml/__init__.py
sensiml/client.py
sensiml/datasets.py
sensiml/pipeline.py
sensiml/render.py
sensiml/sml_runner.py
sensiml/base/__init__.py
sensiml/base/exceptions.py
sensiml/base/snippets.py
sensiml/base/utility.py
sensiml/connection/__init__.py
sensiml/connection/connection.py
sensiml/connection/connection_config.py
sensiml/connection/errors.py
sensiml/data/__init__.py
sensiml/datamanager/__init__.py
sensiml/datamanager/base.py
sensiml/datamanager/capture.py
sensiml/datamanager/capture_configuration.py
sensiml/datamanager/capture_configurations.py
sensiml/datamanager/captures.py
sensiml/datamanager/clientplatformdescription.py
sensiml/datamanager/clientplatformdescriptions.py
sensiml/datamanager/confusion_matrix.py
sensiml/datamanager/custom_functions.py
sensiml/datamanager/deviceconfig.py
sensiml/datamanager/errors.py
sensiml/datamanager/featurefile.py
sensiml/datamanager/featurefiles.py
sensiml/datamanager/foundation_model.py
sensiml/datamanager/function.py
sensiml/datamanager/functions.py
sensiml/datamanager/knowledgepack.py
sensiml/datamanager/label.py
sensiml/datamanager/labelvalue.py
sensiml/datamanager/library_pack.py
sensiml/datamanager/metadata.py
sensiml/datamanager/metadata_relationship.py
sensiml/datamanager/metadata_value.py
sensiml/datamanager/modelresults.py
sensiml/datamanager/pipeline.py
sensiml/datamanager/project.py
sensiml/datamanager/projects.py
sensiml/datamanager/queries.py
sensiml/datamanager/query.py
sensiml/datamanager/sandbox.py
sensiml/datamanager/sandboxes.py
sensiml/datamanager/segment.py
sensiml/datamanager/segmenter.py
sensiml/datamanager/team.py
sensiml/dclproj/__init__.py
sensiml/dclproj/confusion_matrix.py
sensiml/dclproj/csv_to_dcli.py
sensiml/dclproj/datasegments.py
sensiml/dclproj/dclproj.py
sensiml/dclproj/upload.py
sensiml/dclproj/utils.py
sensiml/dclproj/vizualization.py
sensiml/image/__init__.py
sensiml/image/sensiml.png
sensiml/method_calls/__init__.py
sensiml/method_calls/augmentationcall.py
sensiml_dev-2023.1.2.dist-info/LICENSE
sensiml_dev-2023.1.2.dist-info/METADATA
sensiml_dev-2023.1.2.dist-info/WHEEL
sensiml_dev-2023.1.2.dist-info/top_level.txt
sensiml_dev-2023.1.2.dist-info/RECORD
