Metadata-Version: 2.1
Name: sensiml-dev
Version: 2023.1.2
Summary: SensiML Analytic Suite Python Dev Client
Home-page: UNKNOWN
Author: SensiML
Author-email: support@sensiml.com
License: Proprietary
Platform: UNKNOWN
Classifier: Operating System :: OS Independent
Classifier: Programming Language :: Python :: 3.4
Classifier: Programming Language :: Python :: 3.5
Classifier: Programming Language :: Python :: 3.6
Classifier: Programming Language :: Python :: 3.7
License-File: LICENSE
Requires-Dist: cookiejar (==0.0.2)
Requires-Dist: requests (>=2.14.2)
Requires-Dist: requests-oauthlib (>=0.7.0)
Requires-Dist: appdirs (==1.4.3)
Requires-Dist: semantic-version (>=2.6.0)
Requires-Dist: numpy
Requires-Dist: pandas
Requires-Dist: matplotlib
Requires-Dist: prompt-toolkit
Requires-Dist: seaborn
Requires-Dist: wurlitzer
Requires-Dist: tabulate
